clearREPL/__init__.py
clearREPL/clearREPL.py
clearrepl-0.1.0.dist-info/licenses/LICENSE
clearrepl-0.1.0.dist-info/METADATA
clearrepl-0.1.0.dist-info/WHEEL
clearrepl-0.1.0.dist-info/top_level.txt
clearrepl-0.1.0.dist-info/RECORD
