Metadata-Version: 2.4
Name: clearREPL
Version: 0.1.0
Summary: 简单的Python清理屏幕的程序
Author-email: EbenezerDavid <2331858952@qq.com>
License: MIT License
Project-URL: Homepage, https://github.com/Ebenezer/pyclear
Classifier: Programming Language :: Python :: 3
Classifier: License :: OSI Approved :: MIT License
Classifier: Operating System :: OS Independent
Requires-Python: >=3.6
License-File: LICENSE
Dynamic: license-file
